pcodec/__init__.py
pcodec/pcodec.cpython-310-aarch64-linux-gnu.so
pcodec-1.0.0.dist-info/METADATA
pcodec-1.0.0.dist-info/WHEEL
pcodec-1.0.0.dist-info/RECORD
