Metadata-Version: 2.4
Name: pcodec
Version: 1.0.0
Requires-Dist: numpy
Summary: Good compression for numerical sequences
Keywords: compression,numerical
Author-email: mwlon <m.w.loncaric@gmail.com>
License-Expression: Apache-2.0
Project-URL: Repository, https://github.com/pcodec/pcodec
